doubo/__about__.py
doubo/__init__.py
doubo/cli.py
doubo-1.0.dist-info/LICENSE
doubo-1.0.dist-info/METADATA
doubo-1.0.dist-info/WHEEL
doubo-1.0.dist-info/entry_points.txt
doubo-1.0.dist-info/top_level.txt
doubo-1.0.dist-info/RECORD
